fdet/__init__.py
fdet/detector.py
fdet/mtcnn.py
fdet/retinaface.py
fdet/cli/__init__.py
fdet/cli/main.py
fdet/utils/__init__.py
fdet/utils/errors.py
fdet/utils/io.py
fdet-0.2.1.dist-info/LICENSE
fdet-0.2.1.dist-info/METADATA
fdet-0.2.1.dist-info/WHEEL
fdet-0.2.1.dist-info/entry_points.txt
fdet-0.2.1.dist-info/top_level.txt
fdet-0.2.1.dist-info/RECORD
